LICENSE
README.md
pyproject.toml
setup.py
src/py_raccoon/__init__.py
src/py_raccoon/sampling.pyi
src/py_raccoon/sampling.pyx
src/py_raccoon/spanning_trees.pxd
src/py_raccoon/spanning_trees.pyi
src/py_raccoon/spanning_trees.pyx
src/py_raccoon/utils.py
src/py_raccoon.egg-info/PKG-INFO
src/py_raccoon.egg-info/SOURCES.txt
src/py_raccoon.egg-info/dependency_links.txt
src/py_raccoon.egg-info/requires.txt
src/py_raccoon.egg-info/top_level.txt