Metadata-Version: 2.1
Name: py-raccoon
Version: 1.0.0
Summary: PyRaCCooN: Random Cell Complexes on Networks
Author-email: Josef Hoppe <hoppe@cs.rwth-aachen.de>
Project-URL: Homepage, https://github.com/josefhoppe/py-racoon
Project-URL: Bug Tracker, https://github.com/josefhoppe/py-racoon/issues
Classifier: Programming Language :: Python :: 3
Classifier: License :: OSI Approved :: MIT License
Classifier: Operating System :: OS Independent
Requires-Python: >=3.11
License-File: LICENSE
Requires-Dist: networkx
Requires-Dist: numpy>=1.20.0
Requires-Dist: scipy>=1.10.0
Provides-Extra: test
Requires-Dist: pytest-cov; extra == "test"
